elias/__init__.py
elias/ai.py
elias/check.py
elias/config_env_variable.py
elias/datamove.py
elias/etl.py
elias/ollama_client.py
elias/picture.py
elias/text_similarity.py
elias/usual.py
elias/wechat.py
elias/Scripts/MysqlTool.py
elias/Scripts/__init__.py
elias/Scripts/douyin.py
elias/Scripts/function_calling.py
elias/Scripts/image_check.py
elias/Scripts/jd.py
elias/Scripts/name_in_db.py
elias/Scripts/py_clickhouse.py
elias/Scripts/vm_clickhouse.py
elias/Scripts/youdao.py
elias/datax/__init__.py
elias/datax/auto_create_table.py
elias/datax/job.py
elias/datax/main.py
elias/datax/reader.py
elias/datax/run.py
elias/datax/writer.py
eliasliu-0.1.77.dist-info/METADATA
eliasliu-0.1.77.dist-info/WHEEL
eliasliu-0.1.77.dist-info/top_level.txt
eliasliu-0.1.77.dist-info/RECORD
