Metadata-Version: 2.4
Name: eliasliu
Version: 0.1.77
Summary: A very easy tool to deal your data
Home-page: https://github.com/tenbj/elias
Author: Elias Liu 刘益廷
Author-email: liuyiting120@126.com
Classifier: Development Status :: 3 - Alpha
Classifier: Intended Audience :: Developers
Classifier: License :: OSI Approved :: MIT License
Classifier: Programming Language :: Python :: 3
Classifier: Programming Language :: Python :: 3.6
Classifier: Programming Language :: Python :: 3.7
Classifier: Programming Language :: Python :: 3.8
Classifier: Programming Language :: Python :: 3.9
Classifier: Programming Language :: Python :: 3.10
Classifier: Programming Language :: Python :: 3.11
Classifier: Programming Language :: Python :: 3.12
Classifier: Programming Language :: Python :: 3.13
Requires-Dist: pymysql
Requires-Dist: pandas
Requires-Dist: sqlalchemy
Requires-Dist: mysql-connector
Requires-Dist: requests
Requires-Dist: mysql-connector-python
Requires-Dist: impyla
Requires-Dist: bs4
Requires-Dist: selenium
Requires-Dist: loguru
Requires-Dist: ollama
Requires-Dist: pillow
Requires-Dist: opencv-python
Requires-Dist: jieba
Requires-Dist: openai
Requires-Dist: elias_ollama
Dynamic: author
Dynamic: author-email
Dynamic: classifier
Dynamic: description
Dynamic: description-content-type
Dynamic: home-page
Dynamic: requires-dist
Dynamic: summary
